fluidityai/RetailChatbotServer.py
fluidityai/__init__.py
fluidityai/fluidity_classes.py
fluidityai/fluidity_examples.py
fluidityai/fluidity_globals.py
fluidityai/fluidity_tests.py
fluidityai/ord.py
fluidityai/pwd.py
fluidityai/taxi.py
fluidityai-0.1.53.dist-info/licenses/LICENSE
fluidityai-0.1.53.dist-info/METADATA
fluidityai-0.1.53.dist-info/WHEEL
fluidityai-0.1.53.dist-info/top_level.txt
fluidityai-0.1.53.dist-info/RECORD
