Metadata-Version: 2.4
Name: fluidityai
Version: 0.1.53
Summary: Classes for AI workflow development
Home-page: https://github.com/AshT-Python/Fluidity
Author: Ash Thakur
Author-email: ash.thakur@yahoo.co.uk
Classifier: Programming Language :: Python :: 3
Classifier: License :: OSI Approved :: MIT License
Classifier: Operating System :: OS Independent
Requires-Python: >=3.6
License-File: LICENSE
Requires-Dist: detoxify==0.5.2
Requires-Dist: llm_guard==0.3.14
Requires-Dist: openai==1.97.1
Requires-Dist: pandas==1.5.3
Requires-Dist: PyPDF2==3.0.1
Requires-Dist: python-docx==1.2.0
Requires-Dist: scikit_learn==1.7.1
Requires-Dist: sentence_transformers==4.1.0
Requires-Dist: duckdb==1.2.2
Requires-Dist: beautifulsoup4==4.13.4
Dynamic: author
Dynamic: author-email
Dynamic: classifier
Dynamic: description
Dynamic: description-content-type
Dynamic: home-page
Dynamic: license-file
Dynamic: requires-dist
Dynamic: requires-python
Dynamic: summary
